nsflow/__init__.py
nsflow/run.py
nsflow/backend/__init__.py
nsflow/backend/main.py
nsflow/backend/api/__init__.py
nsflow/backend/api/proxy.py
nsflow/backend/api/router.py
nsflow/backend/api/v1/__init__.py
nsflow/backend/api/v1/agent_flows.py
nsflow/backend/api/v1/app_configs.py
nsflow/backend/api/v1/audio_endpoints.py
nsflow/backend/api/v1/cruse_endpoints.py
nsflow/backend/api/v1/editor_endpoints.py
nsflow/backend/api/v1/export_endpoints.py
nsflow/backend/api/v1/fast_websocket.py
nsflow/backend/api/v1/fastapi_grpc_endpoints.py
nsflow/backend/api/v1/oneshot_endpoints.py
nsflow/backend/api/v1/vqa_endpoints.py
nsflow/backend/db/database.py
nsflow/backend/db/models.py
nsflow/backend/models/__init__.py
nsflow/backend/models/config_model.py
nsflow/backend/models/editor_models.py
nsflow/backend/trust/rai_service.py
nsflow/backend/trust/sustainability_calculator.py
nsflow/backend/utils/__init__.py
nsflow/backend/utils/agentutils/__init__.py
nsflow/backend/utils/agentutils/agent_log_processor.py
nsflow/backend/utils/agentutils/agent_network_utils.py
nsflow/backend/utils/agentutils/async_streaming_input_processor.py
nsflow/backend/utils/agentutils/ns_concierge_utils.py
nsflow/backend/utils/agentutils/ns_grpc_network_utils.py
nsflow/backend/utils/agentutils/ns_websocket_utils.py
nsflow/backend/utils/editor/hocon_reader.py
nsflow/backend/utils/editor/ops_store.py
nsflow/backend/utils/editor/simple_state_manager.py
nsflow/backend/utils/editor/simple_state_registry.py
nsflow/backend/utils/editor/toolbox_service.py
nsflow/backend/utils/logutils/__init__.py
nsflow/backend/utils/logutils/process_log_bridge.py
nsflow/backend/utils/logutils/websocket_logs_manager.py
nsflow/backend/utils/logutils/websocket_logs_registry.py
nsflow/backend/utils/tools/__init__.py
nsflow/backend/utils/tools/auth_utils.py
nsflow/backend/utils/tools/notebook_generator.py
nsflow/backend/utils/tools/notebook_utils.py
nsflow/backend/utils/tools/ns_config.py
nsflow/backend/utils/tools/ns_configs_registry.py
nsflow-0.6.7.dist-info/licenses/LICENSE.txt
nsflow-0.6.7.dist-info/METADATA
nsflow-0.6.7.dist-info/WHEEL
nsflow-0.6.7.dist-info/entry_points.txt
nsflow-0.6.7.dist-info/top_level.txt
nsflow-0.6.7.dist-info/RECORD
