Metadata-Version: 2.4
Name: nsflow
Version: 0.6.7
Summary: A Neuro-San powered Smart Agent Network Framework
Author: Deepak
License-Expression: Apache-2.0
Project-URL: Homepage, https://github.com/cognizant-ai-lab/nsflow
Project-URL: Repository, https://github.com/cognizant-ai-lab/nsflow
Project-URL: Documentation, https://github.com/cognizant-ai-lab/nsflow#readme
Keywords: NsFlow,NeuroSan,agent-network
Classifier: Programming Language :: Python :: 3
Classifier: Operating System :: OS Independent
Classifier: Development Status :: 4 - Beta
Classifier: Intended Audience :: Developers
Requires-Python: >=3.10
License-File: LICENSE.txt
Requires-Dist: fastapi-cors>=0.0.6
Requires-Dist: fastapi>=0.115.8
Requires-Dist: aiofiles>=24.1.0
Requires-Dist: graphviz==0.20.3
Requires-Dist: leaf-common>=1.2.32
Requires-Dist: nbformat>=5.10.4
Requires-Dist: pydantic>=2.9.2
Requires-Dist: pyhocon>=0.3.61
Requires-Dist: python-dotenv==1.0.1
Requires-Dist: rich>=14.2.0
Requires-Dist: uvicorn>=0.34.0
Requires-Dist: websockets>=14.2
Requires-Dist: wsproto>=1.2.0
Requires-Dist: Werkzeug>=3.1.4
Requires-Dist: gTTS==2.5.4
Requires-Dist: pydub==0.25.1
Requires-Dist: python-multipart==0.0.20
Requires-Dist: SpeechRecognition==3.14.3
Dynamic: license-file
